Workbook
Name UIF_Ceiling: 'Ruleset v1.1 (2025-26)'!$B$15
Name UIF_Employee_Rate: 'Ruleset v1.1 (2025-26)'!$B$16
Name UIF_Employer_Rate: 'Ruleset v1.1 (2025-26)'!$B$17
Name SDL_Rate: 'Ruleset v1.1 (2025-26)'!$B$18
Name SDL_Threshold: 'Ruleset v1.1 (2025-26)'!$B$19
Name Rebate_Primary: 'Ruleset v1.1 (2025-26)'!$G$5

Sheet Scenarios
A1: Scenario ID | B1: Employee Name | C1: Employee ID | D1: Salary (Monthly) | E1: Bonus (Monthly) | F1: Overtime (Monthly) | G1: Start Date | H1: Termination Date
A2: 1 | B2: Thabo Nkosi | C2: EMP001 | D2: 8500 | E2: 0 | F2: 0 | G2: 2025-03-01
A3: 2 | B3: Lindiwe van der Merwe | C3: EMP002 | D3: 25000 | E3: 0 | F3: 0 | G3: 2025-03-01
A4: 3 | B4: Johan Mokoena | C4: EMP003 | D4: 180000 | E4: 0 | F4: 0 | G4: 2025-03-01
A5: 4 | B5: Ayanda Botha | C5: EMP004 | D5: 35000 | E5: 15000 | F5: 0 | G5: 2025-03-01
A6: 5 | B6: Pieter Dlamini | C6: EMP005 | D6: 12000 | E6: 0 | F6: 3500 | G6: 2025-03-01
A7: 6 | B7: Nomsa Smith | C7: EMP006 | D7: 18000 | E7: 0 | F7: 0 | G7: 2025-03-15
A8: 7 | B8: David Mbeki | C8: EMP007 | D8: 22000 | E8: 0 | F8: 0 | G8: 2025-03-01 | H8: 2025-03-20
A9: 8 | B9: Zanele Pretorius | C9: EMP008 | D9: 40000 | E9: 0 | F9: 0 | G9: 2025-03-01
A10: 9 | B10: Michael Mahlangu | C10: EMP009 | D10: 28000 | E10: 5000 | F10: 2000 | G10: 2025-03-01
A11: 10 | B11: Precious Nel | C11: EMP010 | D11: 17712 | E11: 0 | F11: 0 | G11: 2025-03-01
A12: 11 | B12: Andre Zulu | C12: EMP011 | D12: 15000 | E12: 0 | F12: 0 | G12: 2025-03-01
A13: 12 | B13: Naledi Jacobs | C13: EMP012 | D13: 95000 | E13: 20000 | F13: 0 | G13: 2025-03-01

Sheet Inputs
A1: Employee ID | B1: Basic Salary (Monthly) | C1: Bonus (Monthly) | D1: Overtime (Monthly) | E1: Allowances (Monthly) | F1: Other Deductions (Monthly)
A2: EMP001 | B2: =Scenarios!D2 | C2: =Scenarios!E2 | D2: =Scenarios!F2 | E2: 3500 | F2: 1200
A3: EMP002 | B3: =Scenarios!D3 | C3: =Scenarios!E3 | D3: =Scenarios!F3 | E3: 0 | F3: 750
A4: EMP003 | B4: =Scenarios!D4 | C4: =Scenarios!E4 | D4: =Scenarios!F4 | E4: 0 | F4: 750
A5: EMP004 | B5: =Scenarios!D5 | C5: =Scenarios!E5 | D5: =Scenarios!F5 | E5: 2000 | F5: 0
A6: EMP005 | B6: =Scenarios!D6 | C6: =Scenarios!E6 | D6: =Scenarios!F6 | E6: 3500 | F6: 0
A7: EMP006 | B7: =Scenarios!D7 | C7: =Scenarios!E7 | D7: =Scenarios!F7 | E7: 0 | F7: 1200
A8: EMP007 | B8: =Scenarios!D8 | C8: =Scenarios!E8 | D8: =Scenarios!F8 | E8: 5000 | F8: 500
A9: EMP008 | B9: =Scenarios!D9 | C9: =Scenarios!E9 | D9: =Scenarios!F9 | E9: 0 | F9: 750
A10: EMP009 | B10: =Scenarios!D10 | C10: =Scenarios!E10 | D10: =Scenarios!F10 | E10: 3500 | F10: 500
A11: EMP010 | B11: =Scenarios!D11 | C11: =Scenarios!E11 | D11: =Scenarios!F11 | E11: 5000 | F11: 0
A12: EMP011 | B12: =Scenarios!D12 | C12: =Scenarios!E12 | D12: =Scenarios!F12 | E12: 5000 | F12: 0
A13: EMP012 | B13: =Scenarios!D13 | C13: =Scenarios!E13 | D13: =Scenarios!F13 | E13: 0 | F13: 750

Sheet Calculations
A1: Employee ID | B1: Salary | C1: Bonus | D1: Overtime | E1: Allowances | F1: Other Deductions | G1: Gross Monthly | H1: Annualized Gross | I1: PAYE (Monthly) | J1: UIF (Employee) | K1: UIF (Employer) | L1: SDL (Monthly) | M1: Notes
A2: =Inputs!A2 | B2: =XLOOKUP($A2,Inputs!$A:$A,Inputs!$B:$B,0) | C2: =XLOOKUP($A2,Inputs!$A:$A,Inputs!$C:$C,0) | D2: =XLOOKUP($A2,Inputs!$A:$A,Inputs!$D:$D,0) | E2: =XLOOKUP($A2,Inputs!$A:$A,Inputs!$E:$E,0) | F2: =XLOOKUP($A2,Inputs!$A:$A,Inputs!$F:$F,0) | G2: =SUM(B2:E2) | H2: =G2*12 | I2: =LET( Annual, H2, Bracket1, IF(Annual<=237100, Annual*0.18, 0), Bracket2, IF(Annual>237100, MIN(Annual-237100, 133400)*0.26+42678, 0), Bracket3, IF(Annual>370500, MIN(Annual-370500, 142300)*0.31+77362, 0), Bracket4, IF(Annual>512800, MIN(Annual-512800, 160200)*0.36+121475, 0), Bracket5, IF(Annual>673000, MIN(Annual-673000, 184900)*0.39+179147, 0), Bracket6, IF(Annual>857900, MIN(Annual-857900, 959100)*0.41+251258, 0), Bracket7, IF(Annual>1817000, (Annual-1817000)*0.45+644489, 0), TaxAnnual, Bracket1+Bracket2+Bracket3+Bracket4+Bracket5+Bracket6+Bracket7, TaxWithRebate, MAX(0, TaxAnnual-Rebate_Primary), TaxWithRebate/12 ) | J2: =MIN(G2, UIF_Ceiling)*UIF_Employee_Rate | K2: =MIN(G2, UIF_Ceiling)*UIF_Employer_Rate | L2: =IF(Outputs!$B$14>SDL_Threshold, G2*SDL_Rate, 0) | M2: Low income
A3: =Inputs!A3 | B3: =XLOOKUP($A3,Inputs!$A:$A,Inputs!$B:$B,0) | C3: =XLOOKUP($A3,Inputs!$A:$A,Inputs!$C:$C,0) | D3: =XLOOKUP($A3,Inputs!$A:$A,Inputs!$D:$D,0) | E3: =XLOOKUP($A3,Inputs!$A:$A,Inputs!$E:$E,0) | F3: =XLOOKUP($A3,Inputs!$A:$A,Inputs!$F:$F,0) | G3: =SUM(B3:E3) | H3: =G3*12 | I3: =LET( Annual, H3, Bracket1, IF(Annual<=237100, Annual*0.18, 0), Bracket2, IF(Annual>237100, MIN(Annual-237100, 133400)*0.26+42678, 0), Bracket3, IF(Annual>370500, MIN(Annual-370500, 142300)*0.31+77362, 0), Bracket4, IF(Annual>512800, MIN(Annual-512800, 160200)*0.36+121475, 0), Bracket5, IF(Annual>673000, MIN(Annual-673000, 184900)*0.39+179147, 0), Bracket6, IF(Annual>857900, MIN(Annual-857900, 959100)*0.41+251258, 0), Bracket7, IF(Annual>1817000, (Annual-1817000)*0.45+644489, 0), TaxAnnual, Bracket1+Bracket2+Bracket3+Bracket4+Bracket5+Bracket6+Bracket7, TaxWithRebate, MAX(0, TaxAnnual-Rebate_Primary), TaxWithRebate/12 ) | J3: =MIN(G3, UIF_Ceiling)*UIF_Employee_Rate | K3: =MIN(G3, UIF_Ceiling)*UIF_Employer_Rate | L3: =IF(Outputs!$B$14>SDL_Threshold, G3*SDL_Rate, 0) | M3: Above UIF cap
A4: =Inputs!A4 | B4: =XLOOKUP($A4,Inputs!$A:$A,Inputs!$B:$B,0) | C4: =XLOOKUP($A4,Inputs!$A:$A,Inputs!$C:$C,0) | D4: =XLOOKUP($A4,Inputs!$A:$A,Inputs!$D:$D,0) | E4: =XLOOKUP($A4,Inputs!$A:$A,Inputs!$E:$E,0) | F4: =XLOOKUP($A4,Inputs!$A:$A,Inputs!$F:$F,0) | G4: =SUM(B4:E4) | H4: =G4*12 | I4: =LET( Annual, H4, Bracket1, IF(Annual<=237100, Annual*0.18, 0), Bracket2, IF(Annual>237100, MIN(Annual-237100, 133400)*0.26+42678, 0), Bracket3, IF(Annual>370500, MIN(Annual-370500, 142300)*0.31+77362, 0), Bracket4, IF(Annual>512800, MIN(Annual-512800, 160200)*0.36+121475, 0), Bracket5, IF(Annual>673000, MIN(Annual-673000, 184900)*0.39+179147, 0), Bracket6, IF(Annual>857900, MIN(Annual-857900, 959100)*0.41+251258, 0), Bracket7, IF(Annual>1817000, (Annual-1817000)*0.45+644489, 0), TaxAnnual, Bracket1+Bracket2+Bracket3+Bracket4+Bracket5+Bracket6+Bracket7, TaxWithRebate, MAX(0, TaxAnnual-Rebate_Primary), TaxWithRebate/12 ) | J4: =MIN(G4, UIF_Ceiling)*UIF_Employee_Rate | K4: =MIN(G4, UIF_Ceiling)*UIF_Employer_Rate | L4: =IF(Outputs!$B$14>SDL_Threshold, G4*SDL_Rate, 0) | M4: High income
A5: =Inputs!A5 | B5: =XLOOKUP($A5,Inputs!$A:$A,Inputs!$B:$B,0) | C5: =XLOOKUP($A5,Inputs!$A:$A,Inputs!$C:$C,0) | D5: =XLOOKUP($A5,Inputs!$A:$A,Inputs!$D:$D,0) | E5: =XLOOKUP($A5,Inputs!$A:$A,Inputs!$E:$E,0) | F5: =XLOOKUP($A5,Inputs!$A:$A,Inputs!$F:$F,0) | G5: =SUM(B5:E5) | H5: =G5*12 | I5: =LET( Annual, H5, Bracket1, IF(Annual<=237100, Annual*0.18, 0), Bracket2, IF(Annual>237100, MIN(Annual-237100, 133400)*0.26+42678, 0), Bracket3, IF(Annual>370500, MIN(Annual-370500, 142300)*0.31+77362, 0), Bracket4, IF(Annual>512800, MIN(Annual-512800, 160200)*0.36+121475, 0), Bracket5, IF(Annual>673000, MIN(Annual-673000, 184900)*0.39+179147, 0), Bracket6, IF(Annual>857900, MIN(Annual-857900, 959100)*0.41+251258, 0), Bracket7, IF(Annual>1817000, (Annual-1817000)*0.45+644489, 0), TaxAnnual, Bracket1+Bracket2+Bracket3+Bracket4+Bracket5+Bracket6+Bracket7, TaxWithRebate, MAX(0, TaxAnnual-Rebate_Primary), TaxWithRebate/12 ) | J5: =MIN(G5, UIF_Ceiling)*UIF_Employee_Rate | K5: =MIN(G5, UIF_Ceiling)*UIF_Employer_Rate | L5: =IF(Outputs!$B$14>SDL_Threshold, G5*SDL_Rate, 0) | M5: Bonus month
A6: =Inputs!A6 | B6: =XLOOKUP($A6,Inputs!$A:$A,Inputs!$B:$B,0) | C6: =XLOOKUP($A6,Inputs!$A:$A,Inputs!$C:$C,0) | D6: =XLOOKUP($A6,Inputs!$A:$A,Inputs!$D:$D,0) | E6: =XLOOKUP($A6,Inputs!$A:$A,Inputs!$E:$E,0) | F6: =XLOOKUP($A6,Inputs!$A:$A,Inputs!$F:$F,0) | G6: =SUM(B6:E6) | H6: =G6*12 | I6: =LET( Annual, H6, Bracket1, IF(Annual<=237100, Annual*0.18, 0), Bracket2, IF(Annual>237100, MIN(Annual-237100, 133400)*0.26+42678, 0), Bracket3, IF(Annual>370500, MIN(Annual-370500, 142300)*0.31+77362, 0), Bracket4, IF(Annual>512800, MIN(Annual-512800, 160200)*0.36+121475, 0), Bracket5, IF(Annual>673000, MIN(Annual-673000, 184900)*0.39+179147, 0), Bracket6, IF(Annual>857900, MIN(Annual-857900, 959100)*0.41+251258, 0), Bracket7, IF(Annual>1817000, (Annual-1817000)*0.45+644489, 0), TaxAnnual, Bracket1+Bracket2+Bracket3+Bracket4+Bracket5+Bracket6+Bracket7, TaxWithRebate, MAX(0, TaxAnnual-Rebate_Primary), TaxWithRebate/12 ) | J6: =MIN(G6, UIF_Ceiling)*UIF_Employee_Rate | K6: =MIN(G6, UIF_Ceiling)*UIF_Employer_Rate | L6: =IF(Outputs!$B$14>SDL_Threshold, G6*SDL_Rate, 0) | M6: Overtime heavy
A7: =Inputs!A7 | B7: =XLOOKUP($A7,Inputs!$A:$A,Inputs!$B:$B,0) | C7: =XLOOKUP($A7,Inputs!$A:$A,Inputs!$C:$C,0) | D7: =XLOOKUP($A7,Inputs!$A:$A,Inputs!$D:$D,0) | E7: =XLOOKUP($A7,Inputs!$A:$A,Inputs!$E:$E,0) | F7: =XLOOKUP($A7,Inputs!$A:$A,Inputs!$F:$F,0) | G7: =SUM(B7:E7) | H7: =G7*12 | I7: =LET( Annual, H7, Bracket1, IF(Annual<=237100, Annual*0.18, 0), Bracket2, IF(Annual>237100, MIN(Annual-237100, 133400)*0.26+42678, 0), Bracket3, IF(Annual>370500, MIN(Annual-370500, 142300)*0.31+77362, 0), Bracket4, IF(Annual>512800, MIN(Annual-512800, 160200)*0.36+121475, 0), Bracket5, IF(Annual>673000, MIN(Annual-673000, 184900)*0.39+179147, 0), Bracket6, IF(Annual>857900, MIN(Annual-857900, 959100)*0.41+251258, 0), Bracket7, IF(Annual>1817000, (Annual-1817000)*0.45+644489, 0), TaxAnnual, Bracket1+Bracket2+Bracket3+Bracket4+Bracket5+Bracket6+Bracket7, TaxWithRebate, MAX(0, TaxAnnual-Rebate_Primary), TaxWithRebate/12 ) | J7: =MIN(G7, UIF_Ceiling)*UIF_Employee_Rate | K7: =MIN(G7, UIF_Ceiling)*UIF_Employer_Rate | L7: =IF(Outputs!$B$14>SDL_Threshold, G7*SDL_Rate, 0) | M7: New hire mid-month
A8: =Inputs!A8 | B8: =XLOOKUP($A8,Inputs!$A:$A,Inputs!$B:$B,0) | C8: =XLOOKUP($A8,Inputs!$A:$A,Inputs!$C:$C,0) | D8: =XLOOKUP($A8,Inputs!$A:$A,Inputs!$D:$D,0) | E8: =XLOOKUP($A8,Inputs!$A:$A,Inputs!$E:$E,0) | F8: =XLOOKUP($A8,Inputs!$A:$A,Inputs!$F:$F,0) | G8: =SUM(B8:E8) | H8: =G8*12 | I8: =LET( Annual, H8, Bracket1, IF(Annual<=237100, Annual*0.18, 0), Bracket2, IF(Annual>237100, MIN(Annual-237100, 133400)*0.26+42678, 0), Bracket3, IF(Annual>370500, MIN(Annual-370500, 142300)*0.31+77362, 0), Bracket4, IF(Annual>512800, MIN(Annual-512800, 160200)*0.36+121475, 0), Bracket5, IF(Annual>673000, MIN(Annual-673000, 184900)*0.39+179147, 0), Bracket6, IF(Annual>857900, MIN(Annual-857900, 959100)*0.41+251258, 0), Bracket7, IF(Annual>1817000, (Annual-1817000)*0.45+644489, 0), TaxAnnual, Bracket1+Bracket2+Bracket3+Bracket4+Bracket5+Bracket6+Bracket7, TaxWithRebate, MAX(0, TaxAnnual-Rebate_Primary), TaxWithRebate/12 ) | J8: =MIN(G8, UIF_Ceiling)*UIF_Employee_Rate | K8: =MIN(G8, UIF_Ceiling)*UIF_Employer_Rate | L8: =IF(Outputs!$B$14>SDL_Threshold, G8*SDL_Rate, 0) | M8: Termination mid-month
A9: =Inputs!A9 | B9: =XLOOKUP($A9,Inputs!$A:$A,Inputs!$B:$B,0) | C9: =XLOOKUP($A9,Inputs!$A:$A,Inputs!$C:$C,0) | D9: =XLOOKUP($A9,Inputs!$A:$A,Inputs!$D:$D,0) | E9: =XLOOKUP($A9,Inputs!$A:$A,Inputs!$E:$E,0) | F9: =XLOOKUP($A9,Inputs!$A:$A,Inputs!$F:$F,0) | G9: =SUM(B9:E9) | H9: =G9*12 | I9: =LET( Annual, H9, Bracket1, IF(Annual<=237100, Annual*0.18, 0), Bracket2, IF(Annual>237100, MIN(Annual-237100, 133400)*0.26+42678, 0), Bracket3, IF(Annual>370500, MIN(Annual-370500, 142300)*0.31+77362, 0), Bracket4, IF(Annual>512800, MIN(Annual-512800, 160200)*0.36+121475, 0), Bracket5, IF(Annual>673000, MIN(Annual-673000, 184900)*0.39+179147, 0), Bracket6, IF(Annual>857900, MIN(Annual-857900, 959100)*0.41+251258, 0), Bracket7, IF(Annual>1817000, (Annual-1817000)*0.45+644489, 0), TaxAnnual, Bracket1+Bracket2+Bracket3+Bracket4+Bracket5+Bracket6+Bracket7, TaxWithRebate, MAX(0, TaxAnnual-Rebate_Primary), TaxWithRebate/12 ) | J9: =MIN(G9, UIF_Ceiling)*UIF_Employee_Rate | K9: =MIN(G9, UIF_Ceiling)*UIF_Employer_Rate | L9: =IF(Outputs!$B$14>SDL_Threshold, G9*SDL_Rate, 0) | M9: Contractor
A10: =Inputs!A10 | B10: =XLOOKUP($A10,Inputs!$A:$A,Inputs!$B:$B,0) | C10: =XLOOKUP($A10,Inputs!$A:$A,Inputs!$C:$C,0) | D10: =XLOOKUP($A10,Inputs!$A:$A,Inputs!$D:$D,0) | E10: =XLOOKUP($A10,Inputs!$A:$A,Inputs!$E:$E,0) | F10: =XLOOKUP($A10,Inputs!$A:$A,Inputs!$F:$F,0) | G10: =SUM(B10:E10) | H10: =G10*12 | I10: =LET( Annual, H10, Bracket1, IF(Annual<=237100, Annual*0.18, 0), Bracket2, IF(Annual>237100, MIN(Annual-237100, 133400)*0.26+42678, 0), Bracket3, IF(Annual>370500, MIN(Annual-370500, 142300)*0.31+77362, 0), Bracket4, IF(Annual>512800, MIN(Annual-512800, 160200)*0.36+121475, 0), Bracket5, IF(Annual>673000, MIN(Annual-673000, 184900)*0.39+179147, 0), Bracket6, IF(Annual>857900, MIN(Annual-857900, 959100)*0.41+251258, 0), Bracket7, IF(Annual>1817000, (Annual-1817000)*0.45+644489, 0), TaxAnnual, Bracket1+Bracket2+Bracket3+Bracket4+Bracket5+Bracket6+Bracket7, TaxWithRebate, MAX(0, TaxAnnual-Rebate_Primary), TaxWithRebate/12 ) | J10: =MIN(G10, UIF_Ceiling)*UIF_Employee_Rate | K10: =MIN(G10, UIF_Ceiling)*UIF_Employer_Rate | L10: =IF(Outputs!$B$14>SDL_Threshold, G10*SDL_Rate, 0) | M10: Mixed pay
A11: =Inputs!A11 | B11: =XLOOKUP($A11,Inputs!$A:$A,Inputs!$B:$B,0) | C11: =XLOOKUP($A11,Inputs!$A:$A,Inputs!$C:$C,0) | D11: =XLOOKUP($A11,Inputs!$A:$A,Inputs!$D:$D,0) | E11: =XLOOKUP($A11,Inputs!$A:$A,Inputs!$E:$E,0) | F11: =XLOOKUP($A11,Inputs!$A:$A,Inputs!$F:$F,0) | G11: =SUM(B11:E11) | H11: =G11*12 | I11: =LET( Annual, H11, Bracket1, IF(Annual<=237100, Annual*0.18, 0), Bracket2, IF(Annual>237100, MIN(Annual-237100, 133400)*0.26+42678, 0), Bracket3, IF(Annual>370500, MIN(Annual-370500, 142300)*0.31+77362, 0), Bracket4, IF(Annual>512800, MIN(Annual-512800, 160200)*0.36+121475, 0), Bracket5, IF(Annual>673000, MIN(Annual-673000, 184900)*0.39+179147, 0), Bracket6, IF(Annual>857900, MIN(Annual-857900, 959100)*0.41+251258, 0), Bracket7, IF(Annual>1817000, (Annual-1817000)*0.45+644489, 0), TaxAnnual, Bracket1+Bracket2+Bracket3+Bracket4+Bracket5+Bracket6+Bracket7, TaxWithRebate, MAX(0, TaxAnnual-Rebate_Primary), TaxWithRebate/12 ) | J11: =MIN(G11, UIF_Ceiling)*UIF_Employee_Rate | K11: =MIN(G11, UIF_Ceiling)*UIF_Employer_Rate | L11: =IF(Outputs!$B$14>SDL_Threshold, G11*SDL_Rate, 0) | M11: At UIF cap
A12: =Inputs!A12 | B12: =XLOOKUP($A12,Inputs!$A:$A,Inputs!$B:$B,0) | C12: =XLOOKUP($A12,Inputs!$A:$A,Inputs!$C:$C,0) | D12: =XLOOKUP($A12,Inputs!$A:$A,Inputs!$D:$D,0) | E12: =XLOOKUP($A12,Inputs!$A:$A,Inputs!$E:$E,0) | F12: =XLOOKUP($A12,Inputs!$A:$A,Inputs!$F:$F,0) | G12: =SUM(B12:E12) | H12: =G12*12 | I12: =LET( Annual, H12, Bracket1, IF(Annual<=237100, Annual*0.18, 0), Bracket2, IF(Annual>237100, MIN(Annual-237100, 133400)*0.26+42678, 0), Bracket3, IF(Annual>370500, MIN(Annual-370500, 142300)*0.31+77362, 0), Bracket4, IF(Annual>512800, MIN(Annual-512800, 160200)*0.36+121475, 0), Bracket5, IF(Annual>673000, MIN(Annual-673000, 184900)*0.39+179147, 0), Bracket6, IF(Annual>857900, MIN(Annual-857900, 959100)*0.41+251258, 0), Bracket7, IF(Annual>1817000, (Annual-1817000)*0.45+644489, 0), TaxAnnual, Bracket1+Bracket2+Bracket3+Bracket4+Bracket5+Bracket6+Bracket7, TaxWithRebate, MAX(0, TaxAnnual-Rebate_Primary), TaxWithRebate/12 ) | J12: =MIN(G12, UIF_Ceiling)*UIF_Employee_Rate | K12: =MIN(G12, UIF_Ceiling)*UIF_Employer_Rate | L12: =IF(Outputs!$B$14>SDL_Threshold, G12*SDL_Rate, 0) | M12: SME below SDL threshold
A13: =Inputs!A13 | B13: =XLOOKUP($A13,Inputs!$A:$A,Inputs!$B:$B,0) | C13: =XLOOKUP($A13,Inputs!$A:$A,Inputs!$C:$C,0) | D13: =XLOOKUP($A13,Inputs!$A:$A,Inputs!$D:$D,0) | E13: =XLOOKUP($A13,Inputs!$A:$A,Inputs!$E:$E,0) | F13: =XLOOKUP($A13,Inputs!$A:$A,Inputs!$F:$F,0) | G13: =SUM(B13:E13) | H13: =G13*12 | I13: =LET( Annual, H13, Bracket1, IF(Annual<=237100, Annual*0.18, 0), Bracket2, IF(Annual>237100, MIN(Annual-237100, 133400)*0.26+42678, 0), Bracket3, IF(Annual>370500, MIN(Annual-370500, 142300)*0.31+77362, 0), Bracket4, IF(Annual>512800, MIN(Annual-512800, 160200)*0.36+121475, 0), Bracket5, IF(Annual>673000, MIN(Annual-673000, 184900)*0.39+179147, 0), Bracket6, IF(Annual>857900, MIN(Annual-857900, 959100)*0.41+251258, 0), Bracket7, IF(Annual>1817000, (Annual-1817000)*0.45+644489, 0), TaxAnnual, Bracket1+Bracket2+Bracket3+Bracket4+Bracket5+Bracket6+Bracket7, TaxWithRebate, MAX(0, TaxAnnual-Rebate_Primary), TaxWithRebate/12 ) | J13: =MIN(G13, UIF_Ceiling)*UIF_Employee_Rate | K13: =MIN(G13, UIF_Ceiling)*UIF_Employer_Rate | L13: =IF(Outputs!$B$14>SDL_Threshold, G13*SDL_Rate, 0) | M13: Executive

Sheet Outputs
A1: Employee ID | B1: Gross Pay (Monthly) | C1: PAYE | D1: UIF (Employee) | E1: UIF (Employer) | F1: SDL | G1: Net Pay | H1: Employer Cost
A2: =Calculations!A2 | B2: =Calculations!G2 | C2: =Calculations!I2 | D2: =Calculations!J2 | E2: =Calculations!K2 | F2: =Calculations!L2 | G2: =B2-C2-D2-Inputs!F2 | H2: =B2+E2+F2
A3: =Calculations!A3 | B3: =Calculations!G3 | C3: =Calculations!I3 | D3: =Calculations!J3 | E3: =Calculations!K3 | F3: =Calculations!L3 | G3: =B3-C3-D3-Inputs!F3 | H3: =B3+E3+F3
A4: =Calculations!A4 | B4: =Calculations!G4 | C4: =Calculations!I4 | D4: =Calculations!J4 | E4: =Calculations!K4 | F4: =Calculations!L4 | G4: =B4-C4-D4-Inputs!F4 | H4: =B4+E4+F4
A5: =Calculations!A5 | B5: =Calculations!G5 | C5: =Calculations!I5 | D5: =Calculations!J5 | E5: =Calculations!K5 | F5: =Calculations!L5 | G5: =B5-C5-D5-Inputs!F5 | H5: =B5+E5+F5
A6: =Calculations!A6 | B6: =Calculations!G6 | C6: =Calculations!I6 | D6: =Calculations!J6 | E6: =Calculations!K6 | F6: =Calculations!L6 | G6: =B6-C6-D6-Inputs!F6 | H6: =B6+E6+F6
A7: =Calculations!A7 | B7: =Calculations!G7 | C7: =Calculations!I7 | D7: =Calculations!J7 | E7: =Calculations!K7 | F7: =Calculations!L7 | G7: =B7-C7-D7-Inputs!F7 | H7: =B7+E7+F7
A8: =Calculations!A8 | B8: =Calculations!G8 | C8: =Calculations!I8 | D8: =Calculations!J8 | E8: =Calculations!K8 | F8: =Calculations!L8 | G8: =B8-C8-D8-Inputs!F8 | H8: =B8+E8+F8
A9: =Calculations!A9 | B9: =Calculations!G9 | C9: =Calculations!I9 | D9: =Calculations!J9 | E9: =Calculations!K9 | F9: =Calculations!L9 | G9: =B9-C9-D9-Inputs!F9 | H9: =B9+E9+F9
A10: =Calculations!A10 | B10: =Calculations!G10 | C10: =Calculations!I10 | D10: =Calculations!J10 | E10: =Calculations!K10 | F10: =Calculations!L10 | G10: =B10-C10-D10-Inputs!F10 | H10: =B10+E10+F10
A11: =Calculations!A11 | B11: =Calculations!G11 | C11: =Calculations!I11 | D11: =Calculations!J11 | E11: =Calculations!K11 | F11: =Calculations!L11 | G11: =B11-C11-D11-Inputs!F11 | H11: =B11+E11+F11
A12: =Calculations!A12 | B12: =Calculations!G12 | C12: =Calculations!I12 | D12: =Calculations!J12 | E12: =Calculations!K12 | F12: =Calculations!L12 | G12: =B12-C12-D12-Inputs!F12 | H12: =B12+E12+F12
A13: =Calculations!A13 | B13: =Calculations!G13 | C13: =Calculations!I13 | D13: =Calculations!J13 | E13: =Calculations!K13 | F13: =Calculations!L13 | G13: =B13-C13-D13-Inputs!F13 | H13: =B13+E13+F13
A14: Annual Payroll: | B14: =B14*12 | C14: =SUM(C2:C13) | D14: =SUM(D2:D13) | E14: =SUM(E2:E13) | F14: =SUM(F2:F13) | G14: =SUM(G2:G13) | H14: =SUM(H2:H13)

Sheet Ruleset v1.1 (2025-26)
A1: South African Tax Ruleset 2025-26
A3: PAYE Tax Brackets (Annual) | F3: Tax Rebates (Annual)
A4: From (R) | B4: To (R) | C4: Base Tax (R) | D4: Marginal Rate (%) | F4: Category | G4: Rebate (R)
A5: 1 | B5: 237100 | C5: 0 | D5: 0.18 | F5: Primary | G5: 17235
A6: 237101 | B6: 370500 | C6: 42678 | D6: 0.26 | F6: Secondary | G6: 9444
A7: 370501 | B7: 512800 | C7: 77362 | D7: 0.31 | F7: Tertiary | G7: 3145
A8: 512801 | B8: 673000 | C8: 121475 | D8: 0.36
A9: 673001 | B9: 857900 | C9: 179147 | D9: 0.39 | F9: Tax Thresholds (Annual)
A10: 857901 | B10: 1817000 | C10: 251258 | D10: 0.41 | F10: Age Category | G10: Threshold (R)
A11: 1817001 | B11: 99999999 | C11: 644489 | D11: 0.45 | F11: Under 65 | G11: 95750
F12: 65-74 | G12: 148217
A13: UIF & SDL Parameters | F13: 75+ | G13: 165689
A14: Parameter | B14: Value
A15: UIF Ceiling (Monthly) | B15: 17712
A16: UIF Employee Rate | B16: 0.01
A17: UIF Employer Rate | B17: 0.01
A18: SDL Rate | B18: 0.01
A19: SDL Threshold (Annual Payroll) | B19: 500000
A21: Effective Dates
A22: Tax Year: 1 March 2025 - 28 February 2026
A23: Version: Ruleset v1.1 (2025-26)

Sheet Sources & Notes
A1: Sources & Documentation
A3: Sources:
A4: • SARS Tax Tables 2025/26 (https://www.sars.gov.za)
A5: • TaxTim PAYE Calculator and Summaries
A6: • South African Revenue Service - Income Tax Rates
A7: • Department of Labour - UIF Contribution Rates
A8: • Department of Higher Education - SDL Requirements
A10: Important Notes:
A11: • Bonuses are taxed in the month received and included in annual PAYE calculation
A12: • UIF applies to capped remuneration (R17,712 per month as of 2025/26)
A13: • SDL (Skills Development Levy) applies only if annual payroll exceeds R500,000
A14: • Contractors are typically excluded from UIF and SDL (handled via provisional tax)
... A38: Parameter Traceability:
A39: Parameter | B39: Effective Date | C39: Location
A40: PAYE Brackets | B40: 2025-03-01 | C40: 'Ruleset v1.1 (2025-26)'!A5:D11
A41: Tax Rebates | B41: 2025-03-01 | C41: 'Ruleset v1.1 (2025-26)'!F5:G7
A42: UIF Ceiling | B42: 2025-03-01 | C42: 'Ruleset v1.1 (2025-26)'!B15
A43: SDL Threshold | B43: 2025-03-01 | C43: 'Ruleset v1.1 (2025-26)'!B19
